collective.js.videojs-5.8.8-py2.7-nspkg.pth
collective.js.videojs-5.8.8.dist-info/top_level.txt
collective.js.videojs-5.8.8.dist-info/METADATA
collective.js.videojs-5.8.8.dist-info/DESCRIPTION.rst
collective.js.videojs-5.8.8.dist-info/entry_points.txt
collective.js.videojs-5.8.8.dist-info/WHEEL
collective.js.videojs-5.8.8.dist-info/RECORD
collective.js.videojs-5.8.8.dist-info/metadata.json
collective.js.videojs-5.8.8.dist-info/namespace_packages.txt
collective/js/videojs/configure.zcml
collective/js/videojs/__init__.py
collective/js/videojs/resources/js/video.min.js
collective/js/videojs/resources/js/video.js
collective/js/videojs/resources/css/video-js.min.css
collective/js/videojs/resources/css/video-js.css
