Metadata-Version: 2.0
Name: collective.js.videojs
Version: 5.8.8
Summary: Get twitter videojs as browser resources
Home-page: https://github.com/collective/collective.js.videojs
Author: Rodrigo Ferreira de Souza aka rodfersou
Author-email: rodfersou@gmail.com
License: gpl
Keywords: plone
Platform: UNKNOWN
Classifier: Environment :: Web Environment
Classifier: License :: OSI Approved :: GNU General Public License (GPL)
Classifier: Operating System :: OS Independent
Classifier: Framework :: Zope2
Classifier: Framework :: Plone
Classifier: Framework :: Plone :: 4.0
Classifier: Framework :: Plone :: 4.1
Classifier: Framework :: Plone :: 4.2
Classifier: Framework :: Plone :: 4.3
Classifier: Programming Language :: Python
Classifier: Programming Language :: Python :: 2.6
Classifier: Programming Language :: Python :: 2.7
Requires-Dist: setuptools
